{
    "name": "Aaron",
    "class": "TRAINER_CLASS_ELITE_FOUR_AARON",
    "items": [],
    "ai_flags": [
        "AI_FLAG_BASIC",
        "AI_FLAG_EXPERT",
		"AI_FLAG_EVAL_ATTACK",
		"AI_FLAG_PRESCIENT"
    ],
    "double_battle": false,
    "party": [
        {
            "species": "SPECIES_RHYPERIOR",
            "form": 0,
            "level": 62,
            "item": "ITEM_LOADED_DICE",
            "moves": [
                "MOVE_ROCK_BLAST",
				"MOVE_CLOSE_COMBAT",
				"MOVE_FIRE_PUNCH",
				"MOVE_STEALTH_ROCK"
            ],
            "power": 0,
            "ball_seal": 0,
			"ivHP": 31,
			"ivATK": 31,
			"ivDEF": 31,
			"ivSPEED": 31,
			"ivSPATK": 31,
			"ivSPDEF": 31,
			"evHP": 176,
			"evATK": 248,
			"evDEF": 0,
			"evSPEED": 0,
			"evSPATK": 0,
			"evSPDEF": 84,
			"nature": 3
        },
        {
            "species": "SPECIES_WEAVILE",
            "form": 0,
            "level": 62,
            "item": "ITEM_LIFE_ORB",
            "moves": [
                "MOVE_KNOCK_OFF",
				"MOVE_ICE_BALL",
				"MOVE_PURSUIT",
				"MOVE_LOW_KICK"
            ],
            "power": 0,
            "ball_seal": 0,
			"ivHP": 31,
			"ivATK": 31,
			"ivDEF": 31,
			"ivSPEED": 31,
			"ivSPATK": 31,
			"ivSPDEF": 31,
			"evHP": 0,
			"evATK": 252,
			"evDEF": 4,
			"evSPEED": 248,
			"evSPATK": 0,
			"evSPDEF": 4,
			"nature": 13
        },
        {
            "species": "SPECIES_RAICHU",
            "form": 0,
            "level": 62,
            "item": "ITEM_AIR_BALLOON",
            "moves": [
                "MOVE_NASTY_PLOT",
				"MOVE_THUNDERBOLT",
				"MOVE_SURF",
				"MOVE_ENCORE"
            ],
            "power": 0,
            "ball_seal": 0,
			"ivHP": 31,
			"ivATK": 31,
			"ivDEF": 31,
			"ivSPEED": 31,
			"ivSPATK": 31,
			"ivSPDEF": 31,
			"evHP": 0,
			"evATK": 0,
			"evDEF": 4,
			"evSPEED": 248,
			"evSPATK": 252,
			"evSPDEF": 4,
			"nature": 10
        },
        {
            "species": "SPECIES_DRAGONITE",
            "form": 0,
            "level": 62,
            "item": "ITEM_LUM_BERRY",
            "moves": [
                "MOVE_DRAGON_DANCE",
				"MOVE_OUTRAGE",
				"MOVE_EARTHQUAKE",
				"MOVE_ROOST"
            ],
            "power": 0,
            "ball_seal": 0,
			"ivHP": 31,
			"ivATK": 31,
			"ivDEF": 31,
			"ivSPEED": 31,
			"ivSPATK": 31,
			"ivSPDEF": 31,
			"evHP": 0,
			"evATK": 248,
			"evDEF": 8,
			"evSPEED": 252,
			"evSPATK": 0,
			"evSPDEF": 0,
			"nature": 13
        },
        {
            "species": "SPECIES_TAUROS",
            "form": 0,
            "level": 62,
            "item": "ITEM_LIECHI_BERRY",
            "moves": [
                "MOVE_EXTREME_SPEED",
				"MOVE_BARRAGE",
				"MOVE_EARTHQUAKE",
				"MOVE_GIGA_IMPACT"
            ],
            "power": 0,
            "ball_seal": 0,
			"ability": 1,
			"ivHP": 31,
			"ivATK": 31,
			"ivDEF": 31,
			"ivSPEED": 31,
			"ivSPATK": 31,
			"ivSPDEF": 31,
			"evHP": 0,
			"evATK": 252,
			"evDEF": 0,
			"evSPEED": 248,
			"evSPATK": 0,
			"evSPDEF": 8,
			"nature": 13
        },
		{
            "species": "SPECIES_EMPOLEON",
            "form": 0,
            "level": 62,
            "item": "ITEM_LEFTOVERS",
            "moves": [
                "MOVE_HYDRO_PUMP",
				"MOVE_ICE_BEAM",
				"MOVE_DEFOG",
				"MOVE_ROOST"
            ],
            "power": 0,
            "ball_seal": 0,
			"ivHP": 31,
			"ivATK": 31,
			"ivDEF": 31,
			"ivSPEED": 31,
			"ivSPATK": 31,
			"ivSPDEF": 31,
			"evHP": 252,
			"evATK": 0,
			"evDEF": 0,
			"evSPEED": 0,
			"evSPATK": 56,
			"evSPDEF": 200,
			"nature": 20
        }
    ]
}