{
    "name": "DragonDogma",
    "class": "TRAINER_CLASS_ACE_TRAINER_MALE",
    "items": [],
    "ai_flags": [
        "AI_FLAG_BASIC",
        "AI_FLAG_EXPERT",
		"AI_FLAG_EVAL_ATTACK"
    ],
    "double_battle": false,
    "party": [
        {
            "species": "SPECIES_GARCHOMP",
            "form": 0,
            "level": 65,
            "item": "ITEM_YACHE_BERRY",
            "moves": [
                "MOVE_STEALTH_ROCK",
                "MOVE_ROCK_SLIDE",
                "MOVE_OUTRAGE",
                "MOVE_EARTHQUAKE"
            ],
            "power": 200,
            "ball_seal": 0,
			"ball_type": "ITEM_ULTRA_BALL"
        },
        {
            "species": "SPECIES_DRAGONITE",
            "form": 0,
            "level": 65,
            "item": "ITEM_LEFTOVERS",
            "moves": [
                "MOVE_ICY_WIND",
                "MOVE_THUNDER_WAVE",
                "MOVE_DRAGON_CLAW",
                "MOVE_ROOST"
            ],
            "power": 200,
            "ball_seal": 0,
			"ball_type": "ITEM_ULTRA_BALL"
        },
        {
            "species": "SPECIES_SALAMENCE",
            "form": 0,
            "level": 66,
            "item": "ITEM_LIFE_ORB",
            "moves": [
                "MOVE_DRAGON_DANCE",
                "MOVE_OUTRAGE",
                "MOVE_EARTHQUAKE",
                "MOVE_FIRE_BLAST"
            ],
            "power": 200,
            "ball_seal": 0,
			"ball_type": "ITEM_ULTRA_BALL"
        }
    ]
}