{
    "name": "Hellen",
    "class": "TRAINER_CLASS_BATTLE_GIRL",
    "items": [],
    "ai_flags": [
        "AI_FLAG_BASIC",
        "AI_FLAG_EXPERT",
		"AI_FLAG_EVAL_ATTACK"
    ],
    "double_battle": false,
    "party": [
        {
            "species": "SPECIES_BRELOOM",
            "form": 0,
            "level": 54,
            "item": "ITEM_LIFE_ORB",
            "moves": [
                "MOVE_WAKE_UP_SLAP",
                "MOVE_SPORE",
                "MOVE_BULLET_SEED",
                "MOVE_SWORDS_DANCE"
            ],
            "power": 255,
            "ball_seal": 0,
			"ball_type": "ITEM_ULTRA_BALL"
        },
        {
            "species": "SPECIES_LOPUNNY",
            "form": 0,
            "level": 54,
            "item": "ITEM_SALAC_BERRY",
            "moves": [
                "MOVE_ENDEAVOR",
                "MOVE_ENDURE",
                "MOVE_QUICK_ATTACK"
            ],
            "power": 255,
            "ball_seal": 0,
			"ball_type": "ITEM_ULTRA_BALL"
        }
    ]
}