{
    "name": "Cedric",
    "class": "TRAINER_CLASS_RIVAL",
    "items": [],
    "ai_flags": [
        "AI_FLAG_BASIC",
        "AI_FLAG_EXPERT",
		"AI_FLAG_BATON_PASS",
		"AI_FLAG_EVAL_ATTACK",
		"AI_FLAG_OMNISCIENT"
    ],
    "double_battle": false,
    "party": [
        {
            "species": "SPECIES_INFERNAPE",
            "form": 0,
            "level": 70,
            "item": "ITEM_FOCUS_SASH",
            "moves": [
                "MOVE_TAUNT",
                "MOVE_STEALTH_ROCK",
                "MOVE_CLOSE_COMBAT",
                "MOVE_OVERHEAT"
            ],
            "power": 255,
            "ball_seal": 6,
			"ball_type": "ITEM_PREMIER_BALL",
			"evHP": 4,
			"evATK": 252,
			"evDEF": 0,
			"evSPEED": 252,
			"evSPATK": 0,
			"evSPDEF": 0,
			"nature": 14
        },
		{
            "species": "SPECIES_PIDGEOT",
            "form": 0,
            "level": 68,
            "item": "ITEM_LIFE_ORB",
            "moves": [
                "MOVE_RAZOR_WIND",
                "MOVE_HEAT_WAVE",
                "MOVE_U_TURN",
                "MOVE_ROOST"
            ],
            "power": 255,
            "ball_seal": 0,
			"evHP": 0,
			"evATK": 0,
			"evDEF": 4,
			"evSPEED": 252,
			"evSPATK": 252,
			"evSPDEF": 0,
			"nature": 14
        },
		{
            "species": "SPECIES_AMPHAROS",
            "form": 0,
            "level": 68,
            "item": "ITEM_LIFE_ORB",
            "moves": [
                "MOVE_DRACO_METEOR",
                "MOVE_ZAP_CANNON",
                "MOVE_FOCUS_BLAST",
                "MOVE_MORNING_SUN"
            ],
            "power": 255,
            "ball_seal": 21,
			"ball_type": "ITEM_GREAT_BALL",
			"evHP": 248,
			"evATK": 0,
			"evDEF": 8,
			"evSPEED": 0,
			"evSPATK": 252,
			"evSPDEF": 0,
			"nature": 15
        },
		{
            "species": "SPECIES_BANETTE",
            "form": 0,
            "level": 68,
            "item": "ITEM_CHOICE_BAND",
            "moves": [
                "MOVE_SHADOW_SNEAK"
            ],
            "power": 255,
            "ball_seal": 0,
			"ball_type": "ITEM_DUSK_BALL",
			"evHP": 128,
			"evATK": 124,
			"evDEF": 0,
			"evSPEED": 252,
			"evSPATK": 0,
			"evSPDEF": 0,
			"nature": 13
        },
		{
            "species": "SPECIES_MEW",
            "form": 0,
            "level": 68,
            "item": "ITEM_LEFTOVERS",
            "moves": [
                "MOVE_COSMIC_POWER",
                "MOVE_DRAGON_DANCE",
                "MOVE_NASTY_PLOT",
                "MOVE_BATON_PASS"
            ],
            "power": 255,
            "ball_seal": 10,
			"ball_type": "ITEM_MASTER_BALL"
        },
		{
            "species": "SPECIES_FLYGON",
            "form": 0,
            "level": 68,
            "item": "ITEM_LIFE_ORB",
            "moves": [
                "MOVE_DRAGON_DANCE",
                "MOVE_OUTRAGE",
                "MOVE_EARTHQUAKE",
                "MOVE_FIRE_BLAST"
            ],
            "power": 255,
            "ball_seal": 21,
			"ball_type": "ITEM_ULTRA_BALL",
			"evHP": 76,
			"evATK": 180,
			"evDEF": 0,
			"evSPEED": 252,
			"evSPATK": 0,
			"evSPDEF": 0,
			"nature": 13
        }
    ]
}